nimbus/__init__.py
nimbus/config.yaml
nimbus/nimbus.py
nimbus/nimbus_cli.py
nimbus/server_public_key.txt
nimbus_cloud-0.0.25.dist-info/LICENSE
nimbus_cloud-0.0.25.dist-info/METADATA
nimbus_cloud-0.0.25.dist-info/WHEEL
nimbus_cloud-0.0.25.dist-info/entry_points.txt
nimbus_cloud-0.0.25.dist-info/top_level.txt
nimbus_cloud-0.0.25.dist-info/RECORD
