Metadata-Version: 2.1
Name: nimbus-cloud
Version: 0.0.25
Summary: A secure and customizable cloud storage system.
Home-page: https://github.com/sakshine108/nimbus/
Author: sakshine108
License-File: LICENSE
Requires-Dist: PyYAML (==6.0.1)
Requires-Dist: cryptography (==41.0.5)
Requires-Dist: humanize (==4.8.0)
Requires-Dist: pathvalidate (==3.2.0)
Requires-Dist: pwinput (==1.0.3)
Requires-Dist: rsa (==4.9)
Requires-Dist: setuptools (==66.1.1)
Requires-Dist: tqdm (==4.66.1)
